{
  "id": 445,
  "name": "European Columbine",
  "menu_id": null,
  "description": null,
  "images": [
    {
      "id": 1043,
      "filename": "1043.jpg",
      "path": "1043.jpg",
      "caption": "European Columbine – petals of the dark violet-blue flowers are stretched to a long curved spur",
      "author": "",
      "order": 1
    },
    {
      "id": 1044,
      "filename": "1044.jpg",
      "path": "1044.jpg",
      "caption": "European Columbine – flower bud",
      "author": "",
      "order": 1
    },
    {
      "id": 1045,
      "filename": "1045.jpg",
      "path": "1045.jpg",
      "caption": "European Columbine – fruits are follicles containing black globular seeds",
      "author": "",
      "order": 2
    },
    {
      "id": 1046,
      "filename": "1046.jpg",
      "path": "1046.jpg",
      "caption": "European Columbine – fruits are follicles containing black globular seeds",
      "author": "",
      "order": 5
    }
  ]
}