{
  "id": 382,
  "title": "Žluťásek čilimníkový",
  "content": "<p>\r\n\t<em>Colias crocea</em></p>\r\n<p>\r\n\t&nbsp;</p>\r\n<p>\r\n\tPočetnost tohoto druhu v Česk&eacute; republice rok od roku kol&iacute;s&aacute;. Jedn&aacute; se totiž o tažn&yacute; druh, kter&yacute; přezimuje v oblasti Středomoř&iacute; a u n&aacute;s se pouze rozmnožuje. Při migraci ho můžeme zastihnout na cel&eacute;m na&scaron;em &uacute;zem&iacute;, včetně nejvy&scaron;&scaron;&iacute;ch horsk&yacute;ch poloh. Migruj&iacute;c&iacute; dospělci hledaj&iacute; biotopy vhodn&eacute; pro rozmnožov&aacute;n&iacute;, kter&yacute;mi mohou b&yacute;t např&iacute;klad pole, železničn&iacute; n&aacute;spy a lomy, pokud zde rostou živn&eacute; rostliny housenek, kter&yacute;mi jsou různ&iacute; z&aacute;stupci čeledi bobovit&yacute;ch (<em>Fabaceae</em>). Prvn&iacute; migranti se objevuj&iacute; již v dubnu. V l&eacute;tě a na podzim se u n&aacute;s vyv&iacute;j&iacute; dal&scaron;&iacute; jedna až dvě generace. Dospělci posledn&iacute; letn&iacute; či podzimn&iacute; generace t&aacute;hnou zpět na jih. V tepl&yacute;ch letech se u n&aacute;s daj&iacute; zastihnout je&scaron;tě v listopadu.</p>\r\n",
  "url": "ziva-priroda/opusteny-vapencovy-lom/zivocichove/zlutasek-cilimnikovy",
  "menu_id": 209,
  "gallery_id": 138
}